hosterNetPython/__init__.py
hosterNetPython/httpServer.py
hosterNetPython/socketServer/__init__.py
hosterNetPython/socketServer/chat.py
hosterNetPython/socketServer/chatC.py
hosterNetPython-0.1.0.dist-info/METADATA
hosterNetPython-0.1.0.dist-info/WHEEL
hosterNetPython-0.1.0.dist-info/top_level.txt
hosterNetPython-0.1.0.dist-info/RECORD
