Metadata-Version: 2.1
Name: hosterNetPython
Version: 0.1.0
Summary: All in one NetPythonHoster
Home-page: https://github.com/lamalice20/hosterNetPython
Author: lamalice20
Author-email: discord974a@gmail.com
Requires-Python: >=3.12.5
Requires-Dist: vidstream
